trophyfetcher/__init__.py
trophyfetcher/app.py
trophyfetcher/config.py
trophyfetcher/logger.py
trophyfetcher-0.1.0.dist-info/DESCRIPTION.rst
trophyfetcher-0.1.0.dist-info/METADATA
trophyfetcher-0.1.0.dist-info/RECORD
trophyfetcher-0.1.0.dist-info/WHEEL
trophyfetcher-0.1.0.dist-info/metadata.json
trophyfetcher-0.1.0.dist-info/top_level.txt
