Metadata-Version: 2.0
Name: trophyfetcher
Version: 0.1.0
Summary: A package used to fetch public information about trophies from PSN.
Home-page: https://github.com/robertomlsoares/trophyfetcher
Author: Roberto Soares
Author-email: robertomlsoares@gmail.com
License: MIT
Keywords: selenium,psn,trophy,fetcher,crawler
Platform: Platform Independent
Classifier: Development Status :: 3 - Alpha
Classifier: Environment :: Web Environment
Classifier: Intended Audience :: Developers
Classifier: License :: OSI Approved :: MIT License
Classifier: Natural Language :: English
Classifier: Operating System :: OS Independent
Classifier: Programming Language :: Python :: 2.7
Classifier: Programming Language :: Python :: Implementation
Classifier: Topic :: Internet :: WWW/HTTP :: Dynamic Content
Classifier: Topic :: Software Development :: Libraries :: Python Modules
Requires-Dist: selenium (>=2.53.2)
